Metadata-Version: 2.1
Name: filter-pyspark
Version: 0.2.0
Summary: filter rename  in pyspark dataframe
Home-page: UNKNOWN
Author-email: ranjitmaity95@gmail.com
License: UNKNOWN
Platform: UNKNOWN
